wt/__init__.py
wt/cli.py
wt/config.py
wt/gitutil.py
wt/hooks.py
wt/lock.py
wt/paths.py
wt/status.py
wt/table.py
wt/vscode.py
wt_cli-0.2.2.dist-info/METADATA
wt_cli-0.2.2.dist-info/WHEEL
wt_cli-0.2.2.dist-info/entry_points.txt
wt_cli-0.2.2.dist-info/licenses/LICENSE.md
wt_cli-0.2.2.dist-info/RECORD
