Metadata-Version: 2.4
Name: wt-cli
Version: 0.2.2
Summary: Zero-friction git worktree manager
License-File: LICENSE.md
Requires-Python: >=3.11
